[
{
"SkinName":"Sĩ Quan Viễn Chinh",
"Preview":"",
"Link":""
},
{
    "SkinName":"Ám Tử Đao",
    "Preview":"",
    "Link":""
    },
    {
        "SkinName":"Quỷ Nguyệt Tướng",
        "Preview":"",
        "Link":""
        },
        {
            "SkinName":"Đao Phủ Tận Thế",
            "Preview":"",
            "Link":""
            },
            {
                "SkinName":"Chiến Binh Trăng Khuyết",
                "Preview":"",
                "Link":""
                },
                {
                    "SkinName":"Thuyền Trưởng Hải Tặc",
                    "Preview":"",
                    "Link":""
                    }
]